patronus_api/__init__.py
patronus_api/_base_client.py
patronus_api/_client.py
patronus_api/_compat.py
patronus_api/_constants.py
patronus_api/_exceptions.py
patronus_api/_files.py
patronus_api/_models.py
patronus_api/_qs.py
patronus_api/_resource.py
patronus_api/_response.py
patronus_api/_streaming.py
patronus_api/_types.py
patronus_api/_version.py
patronus_api/py.typed
patronus_api/_utils/__init__.py
patronus_api/_utils/_logs.py
patronus_api/_utils/_proxy.py
patronus_api/_utils/_reflection.py
patronus_api/_utils/_resources_proxy.py
patronus_api/_utils/_streams.py
patronus_api/_utils/_sync.py
patronus_api/_utils/_transform.py
patronus_api/_utils/_typing.py
patronus_api/_utils/_utils.py
patronus_api/lib/.keep
patronus_api/resources/__init__.py
patronus_api/resources/apps.py
patronus_api/resources/evaluations.py
patronus_api/resources/evaluator_criteria.py
patronus_api/resources/evaluators.py
patronus_api/resources/experiments.py
patronus_api/resources/projects.py
patronus_api/resources/prompts.py
patronus_api/resources/trace_insight.py
patronus_api/resources/whoami.py
patronus_api/resources/otel/__init__.py
patronus_api/resources/otel/logs.py
patronus_api/resources/otel/otel.py
patronus_api/resources/otel/spans.py
patronus_api/types/__init__.py
patronus_api/types/app_list_params.py
patronus_api/types/app_list_response.py
patronus_api/types/evaluation_batch_create_params.py
patronus_api/types/evaluation_batch_create_response.py
patronus_api/types/evaluation_batch_delete_params.py
patronus_api/types/evaluation_evaluate_params.py
patronus_api/types/evaluation_evaluate_response.py
patronus_api/types/evaluation_retrieve_response.py
patronus_api/types/evaluation_search_params.py
patronus_api/types/evaluation_search_response.py
patronus_api/types/evaluator_criteria.py
patronus_api/types/evaluator_criterion_add_revision_params.py
patronus_api/types/evaluator_criterion_add_revision_response.py
patronus_api/types/evaluator_criterion_archive_response.py
patronus_api-0.3.0.dist-info/METADATA
patronus_api-0.3.0.dist-info/WHEEL
patronus_api-0.3.0.dist-info/licenses/LICENSE
patronus_api-0.3.0.dist-info/RECORD
